CHANGELOG.md
MANIFEST.in
README.md
setup.py
pyma/__init__.py
pyma/public.py
pyma.egg-info/PKG-INFO
pyma.egg-info/SOURCES.txt
pyma.egg-info/dependency_links.txt
pyma.egg-info/not-zip-safe
pyma.egg-info/top_level.txt