Metadata-Version: 1.0
Name: pyma
Version: 1.5
Summary: A simple library for executing moving average function on a dataset
Home-page: https://bitbucket.org/aideaucegep/pyma
Author: Pierre-Yves Mathieu
Author-email: github@pywebdesign.net
License: MIT
Platform: UNKNOWN
